nexmo_jwt/__init__.py
nexmo_jwt-1.0.1.dist-info/LICENSE
nexmo_jwt-1.0.1.dist-info/METADATA
nexmo_jwt-1.0.1.dist-info/WHEEL
nexmo_jwt-1.0.1.dist-info/top_level.txt
nexmo_jwt-1.0.1.dist-info/RECORD
