Metadata-Version: 2.1
Name: nexmo-jwt
Version: 1.0.1
Summary: JWT Generator for Nexmo
Home-page: https://github.com/nexmo/nexmo-jwt-python
Author: Diana Rodriguez
Author-email: diana.rodriguezmanrique@vonage.com
License: UNKNOWN
Platform: UNKNOWN
Classifier: Programming Language :: Python :: 3
Classifier: License :: OSI Approved :: MIT License
Classifier: Operating System :: OS Independent
Requires-Python: >=3.4
Requires-Dist: pyjwt (>=1.0.1)
